llama_index/packs/koda_retriever/__init__.py
llama_index/packs/koda_retriever/base.py
llama_index/packs/koda_retriever/constants.py
llama_index/packs/koda_retriever/matrix.py
llama_index_packs_koda_retriever-0.4.1.dist-info/METADATA
llama_index_packs_koda_retriever-0.4.1.dist-info/WHEEL
llama_index_packs_koda_retriever-0.4.1.dist-info/licenses/LICENSE
llama_index_packs_koda_retriever-0.4.1.dist-info/RECORD
