Metadata-Version: 2.4
Name: llama-index-packs-koda-retriever
Version: 0.4.1
Summary: Custom hybrid retriever with alpha tuning and routing.
Author-email: Patrick Miramontes <patdjm7@gmail.com>
License-Expression: MIT
License-File: LICENSE
Requires-Python: <3.12,>=3.9
Requires-Dist: llama-index-core<0.15,>=0.13.0
Requires-Dist: llama-index-readers-wikipedia<0.5,>=0.4.0
Requires-Dist: wikipedia<2,>=1.4.0
